[
    {
        "geonameId": 8633718,
        "name": "Ajingi",
        "children": [
            {
                "geonameId": 9410564,
                "name": "Ajingi",
                "children": [
                    
                ]
            },
            {
                "geonameId": 9410565,
                "name": "Balare",
                "children": [
                    
                ]
            },
            {
                "geonameId": 9410566,
                "name": "Chula",
                "children": [
                    
                ]
            },
            {
                "geonameId": 9410567,
                "name": "Dabin-Kanawa",
                "children": [
                    
                ]
            },
            {
                "geonameId": 9410569,
                "name": "Dundun",
                "children": [
                    
                ]
            },
            {
                "geonameId": 9410571,
                "name": "Gafasa",
                "children": [
                    
                ]
            },
            {
                "geonameId": 9410572,
                "name": "Gurduba",
                "children": [
                    
                ]
            },
            {
                "geonameId": 9410573,
                "name": "Kunkurawa",
                "children": [
                    
                ]
            },
            {
                "geonameId": 9410574,
                "name": "Toranke",
                "children": [
                    
                ]
            },
            {
                "geonameId": 9410575,
                "name": "Unguwar Bai",
                "children": [
                    
                ]
            }
        ]
    },
    {
        "geonameId": 8633720,
        "name": "Albasu",
        "children": [
            {
                "geonameId": 9410568,
                "name": "Albasu Central",
                "children": [
                    
                ]
            },
            {
                "geonameId": 9410502,
                "name": "Bataiya",
                "children": [
                    
                ]
            },
            {
                "geonameId": 9410578,
                "name": "Daho",
                "children": [
                    
                ]
            },
            {
                "geonameId": 9410579,
                "name": "Duja",
                "children": [
                    
                ]
            },
            {
                "geonameId": 9410580,
                "name": "Fanda",
                "children": [
                    
                ]
            },
            {
                "geonameId": 9410581,
                "name": "Faragai",
                "children": [
                    
                ]
            },
            {
                "geonameId": 9410582,
                "name": "Gagarame",
                "children": [
                    
                ]
            },
            {
                "geonameId": 9412367,
                "name": "Hungu",
                "children": [
                    
                ]
            },
            {
                "geonameId": 9410583,
                "name": "Saya-Saya",
                "children": [
                    
                ]
            },
            {
                "geonameId": 9410584,
                "name": "Tsangaya",
                "children": [
                    
                ]
            }
        ]
    },
    {
        "geonameId": 8633696,
        "name": "Bagwai",
        "children": [
            {
                "geonameId": 9410585,
                "name": "Bagwai",
                "children": [
                    
                ]
            },
            {
                "geonameId": 9410570,
                "name": "Dangada",
                "children": [
                    
                ]
            },
            {
                "geonameId": 9410587,
                "name": "Gadanya",
                "children": [
                    
                ]
            },
            {
                "geonameId": 9412459,
                "name": "Gogori",
                "children": [
                    
                ]
            },
            {
                "geonameId": 9410588,
                "name": "Kiyawa",
                "children": [
                    
                ]
            },
            {
                "geonameId": 9410589,
                "name": "Kwajale",
                "children": [
                    
                ]
            },
            {
                "geonameId": 9412460,
                "name": "Rimin Dako",
                "children": [
                    
                ]
            },
            {
                "geonameId": 9410590,
                "name": "Romo",
                "children": [
                    
                ]
            },
            {
                "geonameId": 9410591,
                "name": "Sare-Sare",
                "children": [
                    
                ]
            },
            {
                "geonameId": 9410592,
                "name": "Wuro Bagga",
                "children": [
                    
                ]
            }
        ]
    },
    {
        "geonameId": 7871263,
        "name": "Bebeji",
        "children": [
            {
                "geonameId": 9410593,
                "name": "Anadariya",
                "children": [
                    
                ]
            },
            {
                "geonameId": 9410594,
                "name": "Baguda",
                "children": [
                    
                ]
            },
            {
                "geonameId": 9410596,
                "name": "Bebeji",
                "children": [
                    
                ]
            },
            {
                "geonameId": 9410597,
                "name": "Damau",
                "children": [
                    
                ]
            },
            {
                "geonameId": 9410598,
                "name": "Durmawa",
                "children": [
                    
                ]
            },
            {
                "geonameId": 9410599,
                "name": "Gargai",
                "children": [
                    
                ]
            },
            {
                "geonameId": 9410600,
                "name": "Gwarmai",
                "children": [
                    
                ]
            },
            {
                "geonameId": 9410601,
                "name": "Kofa",
                "children": [
                    
                ]
            },
            {
                "geonameId": 9410605,
                "name": "Kuki",
                "children": [
                    
                ]
            },
            {
                "geonameId": 9410606,
                "name": "Rahama",
                "children": [
                    
                ]
            },
            {
                "geonameId": 9410607,
                "name": "Ranka",
                "children": [
                    
                ]
            },
            {
                "geonameId": 9410602,
                "name": "Rantan",
                "children": [
                    
                ]
            },
            {
                "geonameId": 9410604,
                "name": "Tariwa",
                "children": [
                    
                ]
            },
            {
                "geonameId": 9410608,
                "name": "Wak",
                "children": [
                    
                ]
            }
        ]
    },
    {
        "geonameId": 8633694,
        "name": "Bichi",
        "children": [
            {
                "geonameId": 9410609,
                "name": "Badume",
                "children": [
                    
                ]
            },
            {
                "geonameId": 9412368,
                "name": "Bichi",
                "children": [
                    
                ]
            },
            {
                "geonameId": 9410610,
                "name": "Danzabuwa",
                "children": [
                    
                ]
            },
            {
                "geonameId": 9410611,
                "name": "Fagolo",
                "children": [
                    
                ]
            },
            {
                "geonameId": 9410612,
                "name": "Kau-Kau",
                "children": [
                    
                ]
            },
            {
                "geonameId": 9410613,
                "name": "Kwamarawa",
                "children": [
                    
                ]
            },
            {
                "geonameId": 9412360,
                "name": "Kyalli",
                "children": [
                    
                ]
            },
            {
                "geonameId": 9410615,
                "name": "Muntsira",
                "children": [
                    
                ]
            },
            {
                "geonameId": 9410616,
                "name": "Saye",
                "children": [
                    
                ]
            },
            {
                "geonameId": 9410617,
                "name": "Waire",
                "children": [
                    
                ]
            },
            {
                "geonameId": 9410618,
                "name": "Yallami",
                "children": [
                    
                ]
            }
        ]
    },
    {
        "geonameId": 7910343,
        "name": "Bunkure",
        "children": [
            {
                "geonameId": 9412461,
                "name": "Barkum",
                "children": [
                    
                ]
            },
            {
                "geonameId": 9410619,
                "name": "Bono",
                "children": [
                    
                ]
            },
            {
                "geonameId": 9410620,
                "name": "Bunkure",
                "children": [
                    
                ]
            },
            {
                "geonameId": 9412463,
                "name": "Chirin",
                "children": [
                    
                ]
            },
            {
                "geonameId": 9410622,
                "name": "Gafan",
                "children": [
                    
                ]
            },
            {
                "geonameId": 9410623,
                "name": "Gurjiya",
                "children": [
                    
                ]
            },
            {
                "geonameId": 9410624,
                "name": "Gwamma",
                "children": [
                    
                ]
            },
            {
                "geonameId": 9410625,
                "name": "Kulluwa",
                "children": [
                    
                ]
            },
            {
                "geonameId": 9412466,
                "name": "Kumurya",
                "children": [
                    
                ]
            },
            {
                "geonameId": 9410626,
                "name": "Sanda",
                "children": [
                    
                ]
            }
        ]
    },
    {
        "geonameId": 8633819,
        "name": "Dala",
        "children": [
            {
                "geonameId": 9410928,
                "name": "Adakawa",
                "children": [
                    
                ]
            },
            {
                "geonameId": 9410926,
                "name": "Bakin Ruwa",
                "children": [
                    
                ]
            },
            {
                "geonameId": 9410933,
                "name": "Dala",
                "children": [
                    
                ]
            },
            {
                "geonameId": 9410927,
                "name": "Dogon Nama",
                "children": [
                    
                ]
            },
            {
                "geonameId": 9410936,
                "name": "Gobirawa",
                "children": [
                    
                ]
            },
            {
                "geonameId": 9410934,
                "name": "Gwammaja",
                "children": [
                    
                ]
            },
            {
                "geonameId": 9410931,
                "name": "Kabuwaya",
                "children": [
                    
                ]
            },
            {
                "geonameId": 9410930,
                "name": "Kantudu",
                "children": [
                    
                ]
            },
            {
                "geonameId": 9410932,
                "name": "Kofar Mazugal",
                "children": [
                    
                ]
            },
            {
                "geonameId": 9410935,
                "name": "Kofar Ruwa",
                "children": [
                    
                ]
            },
            {
                "geonameId": 9410923,
                "name": "Madigawa",
                "children": [
                    
                ]
            },
            {
                "geonameId": 9410929,
                "name": "Yalwa",
                "children": [
                    
                ]
            }
        ]
    },
    {
        "geonameId": 8633692,
        "name": "Dambatta",
        "children": [
            {
                "geonameId": 9410627,
                "name": "Ajumawa",
                "children": [
                    
                ]
            },
            {
                "geonameId": 9410629,
                "name": "Dambatta East",
                "children": [
                    
                ]
            },
            {
                "geonameId": 9410630,
                "name": "Dambatta West",
                "children": [
                    
                ]
            },
            {
                "geonameId": 9410631,
                "name": "Fagwalawa",
                "children": [
                    
                ]
            },
            {
                "geonameId": 9410634,
                "name": "Goron Maje",
                "children": [
                    
                ]
            },
            {
                "geonameId": 9410633,
                "name": "Gwanda",
                "children": [
                    
                ]
            },
            {
                "geonameId": 9410632,
                "name": "Gwarabjawa",
                "children": [
                    
                ]
            },
            {
                "geonameId": 9412369,
                "name": "Kore",
                "children": [
                    
                ]
            },
            {
                "geonameId": 9412467,
                "name": "Saidawa",
                "children": [
                    
                ]
            },
            {
                "geonameId": 9412169,
                "name": "San San",
                "children": [
                    
                ]
            }
        ]
    },
    {
        "geonameId": 7871266,
        "name": "Dawakin Kudu",
        "children": [
            {
                "geonameId": 9410636,
                "name": "Dabar Kwari",
                "children": [
                    
                ]
            },
            {
                "geonameId": 9410637,
                "name": "Danbagina",
                "children": [
                    
                ]
            },
            {
                "geonameId": 9410638,
                "name": "Dawaki",
                "children": [
                    
                ]
            },
            {
                "geonameId": 9410639,
                "name": "Dawakiji",
                "children": [
                    
                ]
            },
            {
                "geonameId": 9410640,
                "name": "Dosan",
                "children": [
                    
                ]
            },
            {
                "geonameId": 9410641,
                "name": "Gano",
                "children": [
                    
                ]
            },
            {
                "geonameId": 9412468,
                "name": "Gurjiya",
                "children": [
                    
                ]
            },
            {
                "geonameId": 9410642,
                "name": "Jido",
                "children": [
                    
                ]
            },
            {
                "geonameId": 9412469,
                "name": "Tanburawa",
                "children": [
                    
                ]
            },
            {
                "geonameId": 9410635,
                "name": "Tsakuwa",
                "children": [
                    
                ]
            },
            {
                "geonameId": 9410643,
                "name": "Unguwar Duniya",
                "children": [
                    
                ]
            },
            {
                "geonameId": 9410644,
                "name": "Yan Barau",
                "children": [
                    
                ]
            },
            {
                "geonameId": 9410645,
                "name": "Yankatsari",
                "children": [
                    
                ]
            },
            {
                "geonameId": 9410646,
                "name": "Yargaya",
                "children": [
                    
                ]
            },
            {
                "geonameId": 9410647,
                "name": "Zogarawa",
                "children": [
                    
                ]
            }
        ]
    },
    {
        "geonameId": 8633699,
        "name": "Dawakin Tofa",
        "children": [
            {
                "geonameId": 9412471,
                "name": "Danguguwa",
                "children": [
                    
                ]
            },
            {
                "geonameId": 9410648,
                "name": "Dawaki East",
                "children": [
                    
                ]
            },
            {
                "geonameId": 9410649,
                "name": "Dawaki West",
                "children": [
                    
                ]
            },
            {
                "geonameId": 9410651,
                "name": "Dawanau",
                "children": [
                    
                ]
            },
            {
                "geonameId": 9410652,
                "name": "Ganduje",
                "children": [
                    
                ]
            },
            {
                "geonameId": 9410653,
                "name": "Gargari",
                "children": [
                    
                ]
            },
            {
                "geonameId": 9410654,
                "name": "Jalli",
                "children": [
                    
                ]
            },
            {
                "geonameId": 9410658,
                "name": "Kwa",
                "children": [
                    
                ]
            },
            {
                "geonameId": 9410657,
                "name": "Marke",
                "children": [
                    
                ]
            },
            {
                "geonameId": 9410655,
                "name": "Tattarawa",
                "children": [
                    
                ]
            },
            {
                "geonameId": 9410659,
                "name": "Tumfafi",
                "children": [
                    
                ]
            }
        ]
    },
    {
        "geonameId": 8633727,
        "name": "Doguwa",
        "children": [
            {
                "geonameId": 9410660,
                "name": "Dadin Kowa",
                "children": [
                    
                ]
            },
            {
                "geonameId": 9412472,
                "name": "Dogon Kawo",
                "children": [
                    
                ]
            },
            {
                "geonameId": 9410661,
                "name": "Doguwa",
                "children": [
                    
                ]
            },
            {
                "geonameId": 9410662,
                "name": "Falgore",
                "children": [
                    
                ]
            },
            {
                "geonameId": 9410650,
                "name": "Maraku",
                "children": [
                    
                ]
            },
            {
                "geonameId": 9410656,
                "name": "Riruwai",
                "children": [
                    
                ]
            },
            {
                "geonameId": 9410663,
                "name": "Shere",
                "children": [
                    
                ]
            },
            {
                "geonameId": 9410664,
                "name": "Tagwaye",
                "children": [
                    
                ]
            },
            {
                "geonameId": 9410665,
                "name": "Unguwar Tsohuwa",
                "children": [
                    
                ]
            },
            {
                "geonameId": 9410666,
                "name": "Zainabi",
                "children": [
                    
                ]
            }
        ]
    },
    {
        "geonameId": 7871270,
        "name": "Fagge",
        "children": [
            {
                "geonameId": 9410917,
                "name": "Fagge A",
                "children": [
                    
                ]
            },
            {
                "geonameId": 9410916,
                "name": "Fagge B",
                "children": [
                    
                ]
            },
            {
                "geonameId": 9410918,
                "name": "Fagge C",
                "children": [
                    
                ]
            },
            {
                "geonameId": 9410919,
                "name": "Fagge D1",
                "children": [
                    
                ]
            },
            {
                "geonameId": 9410922,
                "name": "Fagge D2",
                "children": [
                    
                ]
            },
            {
                "geonameId": 9410924,
                "name": "Kwachiri",
                "children": [
                    
                ]
            },
            {
                "geonameId": 9412063,
                "name": "Rijiyar Lemo",
                "children": [
                    
                ]
            },
            {
                "geonameId": 9410921,
                "name": "Sabon Gari East",
                "children": [
                    
                ]
            },
            {
                "geonameId": 9410920,
                "name": "Sabon Gari West",
                "children": [
                    
                ]
            },
            {
                "geonameId": 9410925,
                "name": "Yammata",
                "children": [
                    
                ]
            }
        ]
    },
    {
        "geonameId": 8633693,
        "name": "Gabasawa",
        "children": [
            {
                "geonameId": 9410667,
                "name": "Gabasawa",
                "children": [
                    
                ]
            },
            {
                "geonameId": 9410668,
                "name": "Garun Danga",
                "children": [
                    
                ]
            },
            {
                "geonameId": 9410669,
                "name": "Joda",
                "children": [
                    
                ]
            },
            {
                "geonameId": 9410670,
                "name": "Karmami",
                "children": [
                    
                ]
            },
            {
                "geonameId": 9410671,
                "name": "Mekiya",
                "children": [
                    
                ]
            },
            {
                "geonameId": 9410672,
                "name": "Tarauni",
                "children": [
                    
                ]
            },
            {
                "geonameId": 9410673,
                "name": "Yautar Arewa",
                "children": [
                    
                ]
            },
            {
                "geonameId": 9410674,
                "name": "Yautar Kudu",
                "children": [
                    
                ]
            },
            {
                "geonameId": 9410675,
                "name": "Yumbu",
                "children": [
                    
                ]
            },
            {
                "geonameId": 9410676,
                "name": "Zakirai",
                "children": [
                    
                ]
            },
            {
                "geonameId": 9410576,
                "name": "Zugachi",
                "children": [
                    
                ]
            }
        ]
    },
    {
        "geonameId": 8633724,
        "name": "Garko",
        "children": [
            {
                "geonameId": 9412473,
                "name": "Dal",
                "children": [
                    
                ]
            },
            {
                "geonameId": 9410678,
                "name": "Garin Ali",
                "children": [
                    
                ]
            },
            {
                "geonameId": 9410679,
                "name": "Garko",
                "children": [
                    
                ]
            },
            {
                "geonameId": 9410680,
                "name": "Gurjiya",
                "children": [
                    
                ]
            },
            {
                "geonameId": 9410681,
                "name": "Kafin Malamai",
                "children": [
                    
                ]
            },
            {
                "geonameId": 9410682,
                "name": "Katumari",
                "children": [
                    
                ]
            },
            {
                "geonameId": 9412474,
                "name": "Kwas",
                "children": [
                    
                ]
            },
            {
                "geonameId": 9410683,
                "name": "Raba",
                "children": [
                    
                ]
            },
            {
                "geonameId": 9412371,
                "name": "Sarina",
                "children": [
                    
                ]
            },
            {
                "geonameId": 9410685,
                "name": "Zakarawa",
                "children": [
                    
                ]
            }
        ]
    },
    {
        "geonameId": 7871264,
        "name": "Garum Mallam",
        "children": [
            {
                "geonameId": 9410686,
                "name": "Chiromawa",
                "children": [
                    
                ]
            },
            {
                "geonameId": 9410687,
                "name": "Dakasoye",
                "children": [
                    
                ]
            },
            {
                "geonameId": 9410688,
                "name": "Dorawar Sallau",
                "children": [
                    
                ]
            },
            {
                "geonameId": 9410689,
                "name": "Fankurun",
                "children": [
                    
                ]
            },
            {
                "geonameId": 9410690,
                "name": "Garun Babba",
                "children": [
                    
                ]
            },
            {
                "geonameId": 9410691,
                "name": "Garun Malam",
                "children": [
                    
                ]
            },
            {
                "geonameId": 9410692,
                "name": "Jobawa",
                "children": [
                    
                ]
            },
            {
                "geonameId": 9410586,
                "name": "Kadawa",
                "children": [
                    
                ]
            },
            {
                "geonameId": 9410603,
                "name": "Makwaro",
                "children": [
                    
                ]
            },
            {
                "geonameId": 9410614,
                "name": "Yada Kwari",
                "children": [
                    
                ]
            }
        ]
    },
    {
        "geonameId": 8633719,
        "name": "Gaya",
        "children": [
            {
                "geonameId": 9410693,
                "name": "Balan",
                "children": [
                    
                ]
            },
            {
                "geonameId": 9410694,
                "name": "Gamarya",
                "children": [
                    
                ]
            },
            {
                "geonameId": 9410695,
                "name": "Gamoji",
                "children": [
                    
                ]
            },
            {
                "geonameId": 9410696,
                "name": "Gaya North",
                "children": [
                    
                ]
            },
            {
                "geonameId": 9410697,
                "name": "Gaya South",
                "children": [
                    
                ]
            },
            {
                "geonameId": 9410698,
                "name": "Kademi",
                "children": [
                    
                ]
            },
            {
                "geonameId": 9410699,
                "name": "Kazurawa",
                "children": [
                    
                ]
            },
            {
                "geonameId": 9410700,
                "name": "Maimakawa",
                "children": [
                    
                ]
            },
            {
                "geonameId": 9410701,
                "name": "Shagogo",
                "children": [
                    
                ]
            },
            {
                "geonameId": 9410702,
                "name": "Wudilawa",
                "children": [
                    
                ]
            }
        ]
    },
    {
        "geonameId": 8633700,
        "name": "Gezawa",
        "children": [
            {
                "geonameId": 9410703,
                "name": "Babawa",
                "children": [
                    
                ]
            },
            {
                "geonameId": 9410704,
                "name": "Gawo",
                "children": [
                    
                ]
            },
            {
                "geonameId": 9410705,
                "name": "Gezawa",
                "children": [
                    
                ]
            },
            {
                "geonameId": 9410706,
                "name": "Jogana",
                "children": [
                    
                ]
            },
            {
                "geonameId": 9410707,
                "name": "Ketawa",
                "children": [
                    
                ]
            },
            {
                "geonameId": 9410708,
                "name": "Mesar Tudu",
                "children": [
                    
                ]
            },
            {
                "geonameId": 9410709,
                "name": "Sararin Gezawa",
                "children": [
                    
                ]
            },
            {
                "geonameId": 9410710,
                "name": "Tsamiya Babba",
                "children": [
                    
                ]
            },
            {
                "geonameId": 9410711,
                "name": "Tumbau",
                "children": [
                    
                ]
            },
            {
                "geonameId": 9410712,
                "name": "Wangara",
                "children": [
                    
                ]
            },
            {
                "geonameId": 9410713,
                "name": "Zango",
                "children": [
                    
                ]
            }
        ]
    },
    {
        "geonameId": 8633820,
        "name": "Gwale",
        "children": [
            {
                "geonameId": 9410937,
                "name": "Dandago",
                "children": [
                    
                ]
            },
            {
                "geonameId": 9410940,
                "name": "Diso",
                "children": [
                    
                ]
            },
            {
                "geonameId": 9410939,
                "name": "Dorayi",
                "children": [
                    
                ]
            },
            {
                "geonameId": 9410942,
                "name": "Galadanchi",
                "children": [
                    
                ]
            },
            {
                "geonameId": 9410946,
                "name": "Goron Dutse",
                "children": [
                    
                ]
            },
            {
                "geonameId": 9410948,
                "name": "Gwale",
                "children": [
                    
                ]
            },
            {
                "geonameId": 9410945,
                "name": "Gyaranya",
                "children": [
                    
                ]
            },
            {
                "geonameId": 9410947,
                "name": "Kabuga",
                "children": [
                    
                ]
            },
            {
                "geonameId": 9410944,
                "name": "Mandawari",
                "children": [
                    
                ]
            },
            {
                "geonameId": 9410943,
                "name": "Sani Mai Nagge",
                "children": [
                    
                ]
            }
        ]
    },
    {
        "geonameId": 8633697,
        "name": "Gwarzo",
        "children": [
            {
                "geonameId": 9410715,
                "name": "Getso",
                "children": [
                    
                ]
            },
            {
                "geonameId": 9410716,
                "name": "Gwarzo",
                "children": [
                    
                ]
            },
            {
                "geonameId": 9410714,
                "name": "Jama'A",
                "children": [
                    
                ]
            },
            {
                "geonameId": 9410717,
                "name": "Kara",
                "children": [
                    
                ]
            },
            {
                "geonameId": 9410718,
                "name": "Kutama",
                "children": [
                    
                ]
            },
            {
                "geonameId": 9410719,
                "name": "Lakwaya",
                "children": [
                    
                ]
            },
            {
                "geonameId": 9410721,
                "name": "Madadi",
                "children": [
                    
                ]
            },
            {
                "geonameId": 9410722,
                "name": "Mainika",
                "children": [
                    
                ]
            },
            {
                "geonameId": 9410723,
                "name": "Sabon Birni",
                "children": [
                    
                ]
            },
            {
                "geonameId": 9410724,
                "name": "Unguwar Tudu",
                "children": [
                    
                ]
            }
        ]
    },
    {
        "geonameId": 8633698,
        "name": "Kabo",
        "children": [
            {
                "geonameId": 9410725,
                "name": "Dugabau",
                "children": [
                    
                ]
            },
            {
                "geonameId": 9412464,
                "name": "Durun",
                "children": [
                    
                ]
            },
            {
                "geonameId": 9410726,
                "name": "Gammo",
                "children": [
                    
                ]
            },
            {
                "geonameId": 9410720,
                "name": "Garo",
                "children": [
                    
                ]
            },
            {
                "geonameId": 9410727,
                "name": "Godiya",
                "children": [
                    
                ]
            },
            {
                "geonameId": 9410728,
                "name": "Gude",
                "children": [
                    
                ]
            },
            {
                "geonameId": 9412470,
                "name": "Hawaden Galadima",
                "children": [
                    
                ]
            },
            {
                "geonameId": 9410729,
                "name": "Kabo",
                "children": [
                    
                ]
            },
            {
                "geonameId": 9410730,
                "name": "Kanwa",
                "children": [
                    
                ]
            },
            {
                "geonameId": 9412475,
                "name": "Masanawa",
                "children": [
                    
                ]
            }
        ]
    },
    {
        "geonameId": 8633821,
        "name": "Kano Municipal",
        "children": [
            {
                "geonameId": 9410955,
                "name": "Chedi",
                "children": [
                    
                ]
            },
            {
                "geonameId": 9410503,
                "name": "Dan Agundi",
                "children": [
                    
                ]
            },
            {
                "geonameId": 9410951,
                "name": "Gandu Albasa",
                "children": [
                    
                ]
            },
            {
                "geonameId": 9410957,
                "name": "Jakara",
                "children": [
                    
                ]
            },
            {
                "geonameId": 9410952,
                "name": "Kan Karofi",
                "children": [
                    
                ]
            },
            {
                "geonameId": 9410954,
                "name": "Shahuchi",
                "children": [
                    
                ]
            },
            {
                "geonameId": 9410950,
                "name": "Sharada",
                "children": [
                    
                ]
            },
            {
                "geonameId": 9410949,
                "name": "She She",
                "children": [
                    
                ]
            },
            {
                "geonameId": 9410956,
                "name": "Tudun Nufawa",
                "children": [
                    
                ]
            },
            {
                "geonameId": 9410941,
                "name": "Tudun Wazurchi",
                "children": [
                    
                ]
            },
            {
                "geonameId": 9410953,
                "name": "Yakasai",
                "children": [
                    
                ]
            },
            {
                "geonameId": 9410959,
                "name": "Zaitawa",
                "children": [
                    
                ]
            },
            {
                "geonameId": 9410958,
                "name": "Zango",
                "children": [
                    
                ]
            }
        ]
    },
    {
        "geonameId": 8633721,
        "name": "Karaye",
        "children": [
            {
                "geonameId": 9412476,
                "name": "Daura",
                "children": [
                    
                ]
            },
            {
                "geonameId": 9410731,
                "name": "Kafin Dabga",
                "children": [
                    
                ]
            },
            {
                "geonameId": 9410732,
                "name": "Kurugu",
                "children": [
                    
                ]
            },
            {
                "geonameId": 9410733,
                "name": "Kwanyawa",
                "children": [
                    
                ]
            },
            {
                "geonameId": 9410734,
                "name": "Magajin Gari",
                "children": [
                    
                ]
            },
            {
                "geonameId": 9412478,
                "name": "Magajin Hajji",
                "children": [
                    
                ]
            },
            {
                "geonameId": 9412477,
                "name": "Tudun Kaya",
                "children": [
                    
                ]
            },
            {
                "geonameId": 9410735,
                "name": "Turawa",
                "children": [
                    
                ]
            },
            {
                "geonameId": 9410736,
                "name": "Yammedi",
                "children": [
                    
                ]
            },
            {
                "geonameId": 9412479,
                "name": "Yola",
                "children": [
                    
                ]
            }
        ]
    },
    {
        "geonameId": 8633723,
        "name": "Kibiya",
        "children": [
            {
                "geonameId": 9410737,
                "name": "Durba",
                "children": [
                    
                ]
            },
            {
                "geonameId": 9410738,
                "name": "Fammar",
                "children": [
                    
                ]
            },
            {
                "geonameId": 9410741,
                "name": "Fassi",
                "children": [
                    
                ]
            },
            {
                "geonameId": 9410121,
                "name": "Kadigawa",
                "children": [
                    
                ]
            },
            {
                "geonameId": 9410739,
                "name": "Kahu",
                "children": [
                    
                ]
            },
            {
                "geonameId": 9410744,
                "name": "Kibiya 1",
                "children": [
                    
                ]
            },
            {
                "geonameId": 9410743,
                "name": "Kibiya 2",
                "children": [
                    
                ]
            },
            {
                "geonameId": 9410742,
                "name": "Nariya",
                "children": [
                    
                ]
            },
            {
                "geonameId": 9410745,
                "name": "Tarai",
                "children": [
                    
                ]
            },
            {
                "geonameId": 9412480,
                "name": "Unguwar Gai",
                "children": [
                    
                ]
            }
        ]
    },
    {
        "geonameId": 7871261,
        "name": "Kiru",
        "children": [
            {
                "geonameId": 9412481,
                "name": "Baawa",
                "children": [
                    
                ]
            },
            {
                "geonameId": 9410746,
                "name": "Badafi",
                "children": [
                    
                ]
            },
            {
                "geonameId": 9410752,
                "name": "Bargoni",
                "children": [
                    
                ]
            },
            {
                "geonameId": 9410747,
                "name": "Bauda",
                "children": [
                    
                ]
            },
            {
                "geonameId": 9412483,
                "name": "Dangora",
                "children": [
                    
                ]
            },
            {
                "geonameId": 9412484,
                "name": "Dansoshiya",
                "children": [
                    
                ]
            },
            {
                "geonameId": 9410748,
                "name": "Dashi",
                "children": [
                    
                ]
            },
            {
                "geonameId": 9410749,
                "name": "Galadimawa",
                "children": [
                    
                ]
            },
            {
                "geonameId": 9410750,
                "name": "Kiru",
                "children": [
                    
                ]
            },
            {
                "geonameId": 9410751,
                "name": "Kogo",
                "children": [
                    
                ]
            },
            {
                "geonameId": 9412486,
                "name": "Maraku",
                "children": [
                    
                ]
            },
            {
                "geonameId": 9410753,
                "name": "Tsaudawa",
                "children": [
                    
                ]
            },
            {
                "geonameId": 9410755,
                "name": "Yako",
                "children": [
                    
                ]
            },
            {
                "geonameId": 9410756,
                "name": "Yalwa",
                "children": [
                    
                ]
            },
            {
                "geonameId": 9410757,
                "name": "Zuwo",
                "children": [
                    
                ]
            }
        ]
    },
    {
        "geonameId": 7871268,
        "name": "Kumbotso",
        "children": [
            {
                "geonameId": 9410966,
                "name": "Chalawa",
                "children": [
                    
                ]
            },
            {
                "geonameId": 9410969,
                "name": "Chiranchi",
                "children": [
                    
                ]
            },
            {
                "geonameId": 9410968,
                "name": "Dan Maliki",
                "children": [
                    
                ]
            },
            {
                "geonameId": 9410972,
                "name": "Danbare",
                "children": [
                    
                ]
            },
            {
                "geonameId": 9410964,
                "name": "Garun Gawa",
                "children": [
                    
                ]
            },
            {
                "geonameId": 9410960,
                "name": "Kumbotso",
                "children": [
                    
                ]
            },
            {
                "geonameId": 9410967,
                "name": "Kureken Sani",
                "children": [
                    
                ]
            },
            {
                "geonameId": 9410970,
                "name": "Mariri",
                "children": [
                    
                ]
            },
            {
                "geonameId": 9410965,
                "name": "Naibawa",
                "children": [
                    
                ]
            },
            {
                "geonameId": 9410963,
                "name": "Panshekara",
                "children": [
                    
                ]
            },
            {
                "geonameId": 9410961,
                "name": "Unguwar Rimi",
                "children": [
                    
                ]
            }
        ]
    },
    {
        "geonameId": 7910326,
        "name": "Kunchi",
        "children": [
            {
                "geonameId": 9410758,
                "name": "Bumai",
                "children": [
                    
                ]
            },
            {
                "geonameId": 9410759,
                "name": "Garun Sheme",
                "children": [
                    
                ]
            },
            {
                "geonameId": 9410760,
                "name": "Gwarmai",
                "children": [
                    
                ]
            },
            {
                "geonameId": 9410761,
                "name": "Kasuwar Kuka",
                "children": [
                    
                ]
            },
            {
                "geonameId": 9410762,
                "name": "Kunchi",
                "children": [
                    
                ]
            },
            {
                "geonameId": 9410763,
                "name": "Matan Fada",
                "children": [
                    
                ]
            },
            {
                "geonameId": 9410764,
                "name": "Ridawa",
                "children": [
                    
                ]
            },
            {
                "geonameId": 9410765,
                "name": "Shamakawa",
                "children": [
                    
                ]
            },
            {
                "geonameId": 9412487,
                "name": "Shuwaki",
                "children": [
                    
                ]
            },
            {
                "geonameId": 9412482,
                "name": "Yandadi",
                "children": [
                    
                ]
            }
        ]
    },
    {
        "geonameId": 7871265,
        "name": "Kura",
        "children": [
            {
                "geonameId": 9410766,
                "name": "Dalili",
                "children": [
                    
                ]
            },
            {
                "geonameId": 9410767,
                "name": "Dan Hassan",
                "children": [
                    
                ]
            },
            {
                "geonameId": 9410768,
                "name": "Dukawa",
                "children": [
                    
                ]
            },
            {
                "geonameId": 9410769,
                "name": "Gundutse",
                "children": [
                    
                ]
            },
            {
                "geonameId": 9410770,
                "name": "Karfi",
                "children": [
                    
                ]
            },
            {
                "geonameId": 9410771,
                "name": "Kosawa",
                "children": [
                    
                ]
            },
            {
                "geonameId": 9410772,
                "name": "Kurun Sumau",
                "children": [
                    
                ]
            },
            {
                "geonameId": 9410773,
                "name": "Rigar Duka",
                "children": [
                    
                ]
            },
            {
                "geonameId": 9412488,
                "name": "Sarkin Kura",
                "children": [
                    
                ]
            },
            {
                "geonameId": 9410774,
                "name": "Tanawa",
                "children": [
                    
                ]
            }
        ]
    },
    {
        "geonameId": 8633717,
        "name": "Madobi",
        "children": [
            {
                "geonameId": 9410775,
                "name": "Burji",
                "children": [
                    
                ]
            },
            {
                "geonameId": 9410776,
                "name": "Cinkoso",
                "children": [
                    
                ]
            },
            {
                "geonameId": 9410777,
                "name": "Galinja",
                "children": [
                    
                ]
            },
            {
                "geonameId": 9410778,
                "name": "Gora",
                "children": [
                    
                ]
            },
            {
                "geonameId": 9410779,
                "name": "Kafin Agur",
                "children": [
                    
                ]
            },
            {
                "geonameId": 9410780,
                "name": "Kanwa",
                "children": [
                    
                ]
            },
            {
                "geonameId": 9410781,
                "name": "Kauran Mata",
                "children": [
                    
                ]
            },
            {
                "geonameId": 9410782,
                "name": "Kubaraci",
                "children": [
                    
                ]
            },
            {
                "geonameId": 9410783,
                "name": "Kwankwaso",
                "children": [
                    
                ]
            },
            {
                "geonameId": 9410784,
                "name": "Madobi",
                "children": [
                    
                ]
            },
            {
                "geonameId": 9410785,
                "name": "Rikadawa",
                "children": [
                    
                ]
            },
            {
                "geonameId": 9410786,
                "name": "Yakun",
                "children": [
                    
                ]
            }
        ]
    },
    {
        "geonameId": 7910325,
        "name": "Makoda",
        "children": [
            {
                "geonameId": 9410787,
                "name": "Babbar Ruga",
                "children": [
                    
                ]
            },
            {
                "geonameId": 9410788,
                "name": "Durma",
                "children": [
                    
                ]
            },
            {
                "geonameId": 9410789,
                "name": "Jibga",
                "children": [
                    
                ]
            },
            {
                "geonameId": 9410790,
                "name": "Kadan Dani",
                "children": [
                    
                ]
            },
            {
                "geonameId": 9410791,
                "name": "Koguna",
                "children": [
                    
                ]
            },
            {
                "geonameId": 9410793,
                "name": "Maitsidau",
                "children": [
                    
                ]
            },
            {
                "geonameId": 9410124,
                "name": "Makoda",
                "children": [
                    
                ]
            },
            {
                "geonameId": 9410794,
                "name": "Satame",
                "children": [
                    
                ]
            },
            {
                "geonameId": 9410792,
                "name": "Tabo",
                "children": [
                    
                ]
            },
            {
                "geonameId": 9410795,
                "name": "Tangaji",
                "children": [
                    
                ]
            },
            {
                "geonameId": 9410796,
                "name": "Wailare",
                "children": [
                    
                ]
            }
        ]
    },
    {
        "geonameId": 7910323,
        "name": "Minjibir",
        "children": [
            {
                "geonameId": 9410797,
                "name": "Azore",
                "children": [
                    
                ]
            },
            {
                "geonameId": 9410798,
                "name": "Gandurwawa",
                "children": [
                    
                ]
            },
            {
                "geonameId": 9410799,
                "name": "Kantama",
                "children": [
                    
                ]
            },
            {
                "geonameId": 9410800,
                "name": "Kunya",
                "children": [
                    
                ]
            },
            {
                "geonameId": 9410801,
                "name": "Kuru",
                "children": [
                    
                ]
            },
            {
                "geonameId": 9412489,
                "name": "Kwarkiya",
                "children": [
                    
                ]
            },
            {
                "geonameId": 9410803,
                "name": "Minjibir",
                "children": [
                    
                ]
            },
            {
                "geonameId": 9410804,
                "name": "Sarbi",
                "children": [
                    
                ]
            },
            {
                "geonameId": 9410805,
                "name": "Tsakiya",
                "children": [
                    
                ]
            },
            {
                "geonameId": 9410806,
                "name": "Tsakuwa",
                "children": [
                    
                ]
            },
            {
                "geonameId": 9410807,
                "name": "Wasai",
                "children": [
                    
                ]
            }
        ]
    },
    {
        "geonameId": 8633818,
        "name": "Nassarawa",
        "children": [
            {
                "geonameId": 9411000,
                "name": "Dakata",
                "children": [
                    
                ]
            },
            {
                "geonameId": 9411003,
                "name": "Gama",
                "children": [
                    
                ]
            },
            {
                "geonameId": 9410998,
                "name": "Gawuna",
                "children": [
                    
                ]
            },
            {
                "geonameId": 9410995,
                "name": "Giginyu",
                "children": [
                    
                ]
            },
            {
                "geonameId": 9410999,
                "name": "Gwagwarwa",
                "children": [
                    
                ]
            },
            {
                "geonameId": 9412070,
                "name": "Hotoro North",
                "children": [
                    
                ]
            },
            {
                "geonameId": 9410990,
                "name": "Hotoro South",
                "children": [
                    
                ]
            },
            {
                "geonameId": 9411001,
                "name": "Kaura Goje",
                "children": [
                    
                ]
            },
            {
                "geonameId": 9410996,
                "name": "Kawaji",
                "children": [
                    
                ]
            },
            {
                "geonameId": 9411002,
                "name": "Tudun Murtala",
                "children": [
                    
                ]
            },
            {
                "geonameId": 9410997,
                "name": "Tudun Wada",
                "children": [
                    
                ]
            }
        ]
    },
    {
        "geonameId": 8633722,
        "name": "Rano",
        "children": [
            {
                "geonameId": 9410808,
                "name": "Dawaki",
                "children": [
                    
                ]
            },
            {
                "geonameId": 9410811,
                "name": "Lausu",
                "children": [
                    
                ]
            },
            {
                "geonameId": 9410813,
                "name": "Madachi",
                "children": [
                    
                ]
            },
            {
                "geonameId": 9410814,
                "name": "Rano",
                "children": [
                    
                ]
            },
            {
                "geonameId": 9410815,
                "name": "Rurum Sabon Gari",
                "children": [
                    
                ]
            },
            {
                "geonameId": 9410816,
                "name": "Rurum Tsohon Gari",
                "children": [
                    
                ]
            },
            {
                "geonameId": 9410818,
                "name": "Saji",
                "children": [
                    
                ]
            },
            {
                "geonameId": 9410819,
                "name": "Yalwa",
                "children": [
                    
                ]
            },
            {
                "geonameId": 9410820,
                "name": "Zinyau",
                "children": [
                    
                ]
            },
            {
                "geonameId": 9412491,
                "name": "Zurgu",
                "children": [
                    
                ]
            }
        ]
    },
    {
        "geonameId": 7910327,
        "name": "Rimin Gado",
        "children": [
            {
                "geonameId": 9410809,
                "name": "Butu-Butu",
                "children": [
                    
                ]
            },
            {
                "geonameId": 9410822,
                "name": "Dawakin Gulu",
                "children": [
                    
                ]
            },
            {
                "geonameId": 9410823,
                "name": "Doka Dawa",
                "children": [
                    
                ]
            },
            {
                "geonameId": 9410396,
                "name": "Dugurawa",
                "children": [
                    
                ]
            },
            {
                "geonameId": 9410824,
                "name": "Gulu",
                "children": [
                    
                ]
            },
            {
                "geonameId": 9410825,
                "name": "Jili",
                "children": [
                    
                ]
            },
            {
                "geonameId": 9410826,
                "name": "Karofin Yashi",
                "children": [
                    
                ]
            },
            {
                "geonameId": 9410827,
                "name": "Rimin Gado",
                "children": [
                    
                ]
            },
            {
                "geonameId": 9410828,
                "name": "Sakara Tsa",
                "children": [
                    
                ]
            },
            {
                "geonameId": 9410829,
                "name": "Tamawa",
                "children": [
                    
                ]
            },
            {
                "geonameId": 9410830,
                "name": "Yalwan Danziyal",
                "children": [
                    
                ]
            },
            {
                "geonameId": 9412492,
                "name": "Zango",
                "children": [
                    
                ]
            }
        ]
    },
    {
        "geonameId": 7910328,
        "name": "Rogo",
        "children": [
            {
                "geonameId": 9410832,
                "name": "Beli",
                "children": [
                    
                ]
            },
            {
                "geonameId": 9410833,
                "name": "Falgore",
                "children": [
                    
                ]
            },
            {
                "geonameId": 9410841,
                "name": "Fulatan",
                "children": [
                    
                ]
            },
            {
                "geonameId": 9410836,
                "name": "Gwangwan",
                "children": [
                    
                ]
            },
            {
                "geonameId": 9410839,
                "name": "Jajaye",
                "children": [
                    
                ]
            },
            {
                "geonameId": 9410843,
                "name": "Rogo Ruma",
                "children": [
                    
                ]
            },
            {
                "geonameId": 9410844,
                "name": "Rogo Sabon Gari",
                "children": [
                    
                ]
            },
            {
                "geonameId": 9410849,
                "name": "Ruwan Bago",
                "children": [
                    
                ]
            },
            {
                "geonameId": 9410850,
                "name": "Zarewa",
                "children": [
                    
                ]
            },
            {
                "geonameId": 9410851,
                "name": "Zoza",
                "children": [
                    
                ]
            }
        ]
    },
    {
        "geonameId": 7910340,
        "name": "Shanono",
        "children": [
            {
                "geonameId": 9410842,
                "name": "Alajawa",
                "children": [
                    
                ]
            },
            {
                "geonameId": 9410845,
                "name": "Dutsen Bakoshi",
                "children": [
                    
                ]
            },
            {
                "geonameId": 9412494,
                "name": "Faruruwa",
                "children": [
                    
                ]
            },
            {
                "geonameId": 9410837,
                "name": "Goron Dutse",
                "children": [
                    
                ]
            },
            {
                "geonameId": 9410838,
                "name": "Kadamu",
                "children": [
                    
                ]
            },
            {
                "geonameId": 9410846,
                "name": "Kokiya",
                "children": [
                    
                ]
            },
            {
                "geonameId": 9410847,
                "name": "Leni",
                "children": [
                    
                ]
            },
            {
                "geonameId": 9412495,
                "name": "Shakogi",
                "children": [
                    
                ]
            },
            {
                "geonameId": 9410834,
                "name": "Shanono",
                "children": [
                    
                ]
            },
            {
                "geonameId": 9410852,
                "name": "Tsaure",
                "children": [
                    
                ]
            }
        ]
    },
    {
        "geonameId": 8633725,
        "name": "Sumaila",
        "children": [
            {
                "geonameId": 9410853,
                "name": "Gala",
                "children": [
                    
                ]
            },
            {
                "geonameId": 9410855,
                "name": "Gani",
                "children": [
                    
                ]
            },
            {
                "geonameId": 9410856,
                "name": "Garfa",
                "children": [
                    
                ]
            },
            {
                "geonameId": 9410858,
                "name": "Gediya",
                "children": [
                    
                ]
            },
            {
                "geonameId": 9410869,
                "name": "Kanawa",
                "children": [
                    
                ]
            },
            {
                "geonameId": 9410864,
                "name": "Magami",
                "children": [
                    
                ]
            },
            {
                "geonameId": 9410865,
                "name": "Masu",
                "children": [
                    
                ]
            },
            {
                "geonameId": 9410860,
                "name": "Rimi",
                "children": [
                    
                ]
            },
            {
                "geonameId": 9410862,
                "name": "Rumo",
                "children": [
                    
                ]
            },
            {
                "geonameId": 9412497,
                "name": "Sitti",
                "children": [
                    
                ]
            },
            {
                "geonameId": 9410863,
                "name": "Sumaila",
                "children": [
                    
                ]
            }
        ]
    },
    {
        "geonameId": 7910341,
        "name": "Takai",
        "children": [
            {
                "geonameId": 9410867,
                "name": "Bagwaro",
                "children": [
                    
                ]
            },
            {
                "geonameId": 9410868,
                "name": "Durbunde",
                "children": [
                    
                ]
            },
            {
                "geonameId": 9410870,
                "name": "Fajewa",
                "children": [
                    
                ]
            },
            {
                "geonameId": 9410859,
                "name": "Falali",
                "children": [
                    
                ]
            },
            {
                "geonameId": 9410875,
                "name": "Farun Ruwa",
                "children": [
                    
                ]
            },
            {
                "geonameId": 9410876,
                "name": "Kachako",
                "children": [
                    
                ]
            },
            {
                "geonameId": 9410877,
                "name": "Karfi",
                "children": [
                    
                ]
            },
            {
                "geonameId": 9410878,
                "name": "Kuka",
                "children": [
                    
                ]
            },
            {
                "geonameId": 9410879,
                "name": "Takai",
                "children": [
                    
                ]
            },
            {
                "geonameId": 9410873,
                "name": "Zuga",
                "children": [
                    
                ]
            }
        ]
    },
    {
        "geonameId": 8633817,
        "name": "Tarauni",
        "children": [
            {
                "geonameId": 9410981,
                "name": "Babban Giji",
                "children": [
                    
                ]
            },
            {
                "geonameId": 9410975,
                "name": "Darmanawa",
                "children": [
                    
                ]
            },
            {
                "geonameId": 9410978,
                "name": "Daurawa",
                "children": [
                    
                ]
            },
            {
                "geonameId": 9410982,
                "name": "Gyadi Gyadi Arewa",
                "children": [
                    
                ]
            },
            {
                "geonameId": 9410977,
                "name": "Gyadi Gyadi Kudu",
                "children": [
                    
                ]
            },
            {
                "geonameId": 9410980,
                "name": "Hotoro",
                "children": [
                    
                ]
            },
            {
                "geonameId": 9410983,
                "name": "Tarauni",
                "children": [
                    
                ]
            },
            {
                "geonameId": 9410973,
                "name": "Unguwa Uku Cikin Gari",
                "children": [
                    
                ]
            },
            {
                "geonameId": 9410976,
                "name": "Unguwa Uku Kauyen Alu",
                "children": [
                    
                ]
            },
            {
                "geonameId": 9410974,
                "name": "Unguwar Gano",
                "children": [
                    
                ]
            }
        ]
    },
    {
        "geonameId": 7701428,
        "name": "Tofa",
        "children": [
            {
                "geonameId": 9412498,
                "name": "Dindere",
                "children": [
                    
                ]
            },
            {
                "geonameId": 9410874,
                "name": "Doka",
                "children": [
                    
                ]
            },
            {
                "geonameId": 9412499,
                "name": "Gajida",
                "children": [
                    
                ]
            },
            {
                "geonameId": 9412500,
                "name": "Ginsawa",
                "children": [
                    
                ]
            },
            {
                "geonameId": 9410880,
                "name": "Janguza",
                "children": [
                    
                ]
            },
            {
                "geonameId": 9410070,
                "name": "Jauben Kudu",
                "children": [
                    
                ]
            },
            {
                "geonameId": 9410071,
                "name": "Kwami",
                "children": [
                    
                ]
            },
            {
                "geonameId": 9410127,
                "name": "Lambu",
                "children": [
                    
                ]
            },
            {
                "geonameId": 9412493,
                "name": "Langel",
                "children": [
                    
                ]
            },
            {
                "geonameId": 9410128,
                "name": "Tofa",
                "children": [
                    
                ]
            },
            {
                "geonameId": 9410519,
                "name": "Unguwar Rimi",
                "children": [
                    
                ]
            },
            {
                "geonameId": 9410544,
                "name": "Wangara",
                "children": [
                    
                ]
            },
            {
                "geonameId": 9410577,
                "name": "Yalwa Karama",
                "children": [
                    
                ]
            },
            {
                "geonameId": 9410840,
                "name": "Yanoko",
                "children": [
                    
                ]
            },
            {
                "geonameId": 9410848,
                "name": "Yarimawa",
                "children": [
                    
                ]
            }
        ]
    },
    {
        "geonameId": 8633695,
        "name": "Tsanyawa",
        "children": [
            {
                "geonameId": 9412372,
                "name": "Daddarawa",
                "children": [
                    
                ]
            },
            {
                "geonameId": 9410882,
                "name": "Dunbulum",
                "children": [
                    
                ]
            },
            {
                "geonameId": 9410883,
                "name": "Gozarki",
                "children": [
                    
                ]
            },
            {
                "geonameId": 9410884,
                "name": "Gurun",
                "children": [
                    
                ]
            },
            {
                "geonameId": 9410885,
                "name": "Kabagiwa",
                "children": [
                    
                ]
            },
            {
                "geonameId": 9410886,
                "name": "Tatsan",
                "children": [
                    
                ]
            },
            {
                "geonameId": 9411608,
                "name": "Tsanyawa",
                "children": [
                    
                ]
            },
            {
                "geonameId": 9412462,
                "name": "Yanganau",
                "children": [
                    
                ]
            },
            {
                "geonameId": 9411923,
                "name": "Yankamaye",
                "children": [
                    
                ]
            },
            {
                "geonameId": 9410887,
                "name": "Zarogi",
                "children": [
                    
                ]
            }
        ]
    },
    {
        "geonameId": 8633726,
        "name": "Tudun Wada",
        "children": [
            {
                "geonameId": 9412502,
                "name": "Baburi",
                "children": [
                    
                ]
            },
            {
                "geonameId": 9410890,
                "name": "Burun-Burun",
                "children": [
                    
                ]
            },
            {
                "geonameId": 9410891,
                "name": "Dalawa",
                "children": [
                    
                ]
            },
            {
                "geonameId": 9410892,
                "name": "Jandutse",
                "children": [
                    
                ]
            },
            {
                "geonameId": 9410893,
                "name": "Jita",
                "children": [
                    
                ]
            },
            {
                "geonameId": 9410894,
                "name": "Karefa",
                "children": [
                    
                ]
            },
            {
                "geonameId": 9412503,
                "name": "Nata-Ala",
                "children": [
                    
                ]
            },
            {
                "geonameId": 9410895,
                "name": "Sabon Gari",
                "children": [
                    
                ]
            },
            {
                "geonameId": 9412504,
                "name": "Shuwaki",
                "children": [
                    
                ]
            },
            {
                "geonameId": 9411161,
                "name": "Tsohon Gari",
                "children": [
                    
                ]
            },
            {
                "geonameId": 9412496,
                "name": "Yaryasa",
                "children": [
                    
                ]
            }
        ]
    },
    {
        "geonameId": 7910324,
        "name": "Ungogo",
        "children": [
            {
                "geonameId": 9410986,
                "name": "Bachirawa",
                "children": [
                    
                ]
            },
            {
                "geonameId": 9410992,
                "name": "Fanisau",
                "children": [
                    
                ]
            },
            {
                "geonameId": 9410991,
                "name": "Gayawa",
                "children": [
                    
                ]
            },
            {
                "geonameId": 9410988,
                "name": "Kadawa",
                "children": [
                    
                ]
            },
            {
                "geonameId": 9410994,
                "name": "Karo",
                "children": [
                    
                ]
            },
            {
                "geonameId": 9410987,
                "name": "Rangaza",
                "children": [
                    
                ]
            },
            {
                "geonameId": 9412506,
                "name": "Rijiyar Zaki",
                "children": [
                    
                ]
            },
            {
                "geonameId": 9410984,
                "name": "Tudun Fulani",
                "children": [
                    
                ]
            },
            {
                "geonameId": 9410993,
                "name": "Ungogo",
                "children": [
                    
                ]
            },
            {
                "geonameId": 9410989,
                "name": "Yada Kunya",
                "children": [
                    
                ]
            },
            {
                "geonameId": 9410985,
                "name": "Zango",
                "children": [
                    
                ]
            }
        ]
    },
    {
        "geonameId": 7729909,
        "name": "Warawa",
        "children": [
            {
                "geonameId": 9410896,
                "name": "Amarawa",
                "children": [
                    
                ]
            },
            {
                "geonameId": 9410897,
                "name": "Danlasan",
                "children": [
                    
                ]
            },
            {
                "geonameId": 9410889,
                "name": "Garin Dau",
                "children": [
                    
                ]
            },
            {
                "geonameId": 9410899,
                "name": "Gogel",
                "children": [
                    
                ]
            },
            {
                "geonameId": 9410857,
                "name": "Imawa",
                "children": [
                    
                ]
            },
            {
                "geonameId": 9410898,
                "name": "Jemagu",
                "children": [
                    
                ]
            },
            {
                "geonameId": 9410904,
                "name": "Jigawa",
                "children": [
                    
                ]
            },
            {
                "geonameId": 9410900,
                "name": "Juma Galadima",
                "children": [
                    
                ]
            },
            {
                "geonameId": 9410901,
                "name": "Katarkawa",
                "children": [
                    
                ]
            },
            {
                "geonameId": 9412501,
                "name": "Madari",
                "children": [
                    
                ]
            },
            {
                "geonameId": 9410902,
                "name": "Tamburawan Gabas",
                "children": [
                    
                ]
            },
            {
                "geonameId": 9412485,
                "name": "Tanagar",
                "children": [
                    
                ]
            },
            {
                "geonameId": 9410866,
                "name": "Warawa",
                "children": [
                    
                ]
            },
            {
                "geonameId": 9410903,
                "name": "Yan Dala",
                "children": [
                    
                ]
            },
            {
                "geonameId": 9410905,
                "name": "Yangizo",
                "children": [
                    
                ]
            }
        ]
    },
    {
        "geonameId": 7910329,
        "name": "Wudil",
        "children": [
            {
                "geonameId": 9410911,
                "name": "Achika",
                "children": [
                    
                ]
            },
            {
                "geonameId": 9410909,
                "name": "Dagumawa",
                "children": [
                    
                ]
            },
            {
                "geonameId": 9410910,
                "name": "Dankaza",
                "children": [
                    
                ]
            },
            {
                "geonameId": 9410907,
                "name": "Darki",
                "children": [
                    
                ]
            },
            {
                "geonameId": 9412505,
                "name": "Indabo",
                "children": [
                    
                ]
            },
            {
                "geonameId": 9410912,
                "name": "Kausani",
                "children": [
                    
                ]
            },
            {
                "geonameId": 9410913,
                "name": "Lajawa",
                "children": [
                    
                ]
            },
            {
                "geonameId": 9410831,
                "name": "Sabon Gari",
                "children": [
                    
                ]
            },
            {
                "geonameId": 9410914,
                "name": "Utai",
                "children": [
                    
                ]
            },
            {
                "geonameId": 9410915,
                "name": "Wudil",
                "children": [
                    
                ]
            }
        ]
    }
]