[
    {
        "geonameId": 2597440,
        "name": "Ave Prefecture",
        "children": [
            
        ]
    },
    {
        "geonameId": 2365263,
        "name": "Golfe Prefecture",
        "children": [
            
        ]
    },
    {
        "geonameId": 2367989,
        "name": "Lacs Prefecture",
        "children": [
            
        ]
    },
    {
        "geonameId": 2364040,
        "name": "Pr\u00e9fecture de Yoto",
        "children": [
            
        ]
    },
    {
        "geonameId": 2363489,
        "name": "Vo Prefecture",
        "children": [
            
        ]
    },
    {
        "geonameId": 2363533,
        "name": "Zio Prefecture",
        "children": [
            
        ]
    }
]